flask_socketio-stubs/METADATA.toml
flask_socketio-stubs/__init__.pyi
flask_socketio-stubs/namespace.pyi
flask_socketio-stubs/py.typed
flask_socketio-stubs/test_client.pyi
types_flask_socketio-5.6.0.20251228.dist-info/licenses/LICENSE
types_flask_socketio-5.6.0.20251228.dist-info/METADATA
types_flask_socketio-5.6.0.20251228.dist-info/WHEEL
types_flask_socketio-5.6.0.20251228.dist-info/top_level.txt
types_flask_socketio-5.6.0.20251228.dist-info/RECORD
